cognite/pygen_spark/__init__.py
cognite/pygen_spark/_version.py
cognite/pygen_spark/config.py
cognite/pygen_spark/fields.py
cognite/pygen_spark/generator.py
cognite/pygen_spark/models.py
cognite/pygen_spark/py.typed
cognite/pygen_spark/templates/__init__.py
cognite/pygen_spark/templates/_http_client.py.jinja
cognite/pygen_spark/templates/_protobuf_parser.py.jinja
cognite/pygen_spark/templates/time_series_datapoints_detailed_udtf.py.jinja
cognite/pygen_spark/templates/time_series_datapoints_udtf.py.jinja
cognite/pygen_spark/templates/time_series_latest_datapoints_udtf.py.jinja
cognite/pygen_spark/templates/time_series_sql_udtf.py.jinja
cognite/pygen_spark/templates/udtf_function.py.jinja
cognite/pygen_spark/templates/udtf_init.py.jinja
cognite/pygen_spark/templates/view_sql.py.jinja
cognite/pygen_spark/time_series_udtfs.py
cognite/pygen_spark/type_converter.py
cognite/pygen_spark/udtf_generator.py
cognite/pygen_spark/utils.py
cognite_pygen_spark-0.2.2.dist-info/WHEEL
cognite_pygen_spark-0.2.2.dist-info/METADATA
cognite_pygen_spark-0.2.2.dist-info/RECORD
