Metadata-Version: 2.4
Name: cognite-pygen-spark
Version: 0.2.2
Summary: Code generation library for creating Python UDTFs from CDF Data Models
Keywords: cognite,cdf,databricks,udtf,code-generation,pyspark
Author: Cognite
Author-email: Cognite <support@cognite.com>
License-Expression: Apache-2.0
Classifier: Development Status :: 3 - Alpha
Classifier: Intended Audience :: Developers
Classifier: Programming Language :: Python :: 3
Classifier: Programming Language :: Python :: 3.10
Classifier: Programming Language :: Python :: 3.11
Classifier: Programming Language :: Python :: 3.12
Requires-Dist: cognite-pygen>=1.2.29
Requires-Dist: cognite-sdk>=7.90.1
Requires-Dist: jinja2>=3.0.0
Requires-Dist: typing-extensions>=4.5.0
Requires-Dist: requests>=2.31.0
Requires-Dist: protobuf>=4.21.0
Requires-Dist: pytest>=8.0.0 ; extra == 'dev'
Requires-Dist: pytest-cov>=6.0.0 ; extra == 'dev'
Requires-Dist: pytest-mock>=3.10.0 ; extra == 'dev'
Requires-Dist: pytest-rerunfailures>=14.0 ; extra == 'dev'
Requires-Dist: pytest-icdiff>=0.8 ; extra == 'dev'
Requires-Dist: black>=24.4.2 ; extra == 'dev'
Requires-Dist: ruff>=0.1.0 ; extra == 'dev'
Requires-Dist: mypy>=1.5.0 ; extra == 'dev'
Requires-Dist: pre-commit>=4.0.0 ; extra == 'dev'
Requires-Dist: pandas>=1.5.3 ; extra == 'dev'
Requires-Dist: pyspark>=4.0.0 ; extra == 'dev'
Requires-Dist: twine>=6.0.0 ; extra == 'dev'
Requires-Dist: typer>=0.9.0 ; extra == 'dev'
Requires-Dist: marko>=2.1.0,<3.0.0 ; extra == 'dev'
Requires-Dist: packaging>=21.3 ; extra == 'dev'
Requires-Python: >=3.10, <4.0
Project-URL: Homepage, https://github.com/cognitedata/pygen-spark
Project-URL: Documentation, https://cognite-pygen-spark.readthedocs.io
Project-URL: Repository, https://github.com/cognitedata/pygen-spark
Project-URL: Issues, https://github.com/cognitedata/pygen-spark/issues
Provides-Extra: dev
